{
  "timestamp": "2025-12-25T10:29:22.096628",
  "scores": {
    "total_hands": 500,
    "total_bids": 3124,
    "total_non_pass_bids": 960,
    "scores": {
      "legality": 100.0,
      "appropriateness": 91.2,
      "conventions": 99.0,
      "consistency": 100,
      "reasonableness": 94.6,
      "game_slam": 37.3,
      "composite": 93.7
    },
    "error_counts": {
      "legality": 0,
      "appropriateness": 84,
      "conventions": 3,
      "game_slam": 94
    },
    "errors": {
      "legality": [],
      "appropriateness": [
        {
          "hand_number": 1,
          "position": "East",
          "bid": "2\u2666",
          "hand_hcp": 12,
          "hand_total_points": 13,
          "hand_shape": "1534",
          "reason": "Bid \u2666 with only 3 cards"
        },
        {
          "hand_number": 1,
          "position": "West",
          "bid": "2\u2665",
          "hand_hcp": 17,
          "hand_total_points": 17,
          "hand_shape": "2344",
          "reason": "Bid \u2665 with only 3 cards"
        },
        {
          "hand_number": 15,
          "position": "North",
          "bid": "4\u2663",
          "hand_hcp": 12,
          "hand_total_points": 12,
          "hand_shape": "3433",
          "reason": "Bid \u2663 with only 3 cards"
        },
        {
          "hand_number": 25,
          "position": "East",
          "bid": "4\u2665",
          "hand_hcp": 14,
          "hand_total_points": 16,
          "hand_shape": "2362",
          "reason": "Bid \u2665 with only 3 cards"
        },
        {
          "hand_number": 33,
          "position": "South",
          "bid": "2\u2663",
          "hand_hcp": 9,
          "hand_total_points": 9,
          "hand_shape": "4243",
          "reason": "Bid \u2663 with only 3 cards"
        },
        {
          "hand_number": 34,
          "position": "South",
          "bid": "2\u2665",
          "hand_hcp": 18,
          "hand_total_points": 20,
          "hand_shape": "6223",
          "reason": "Bid \u2665 with only 2 cards"
        },
        {
          "hand_number": 52,
          "position": "East",
          "bid": "2\u2663",
          "hand_hcp": 12,
          "hand_total_points": 12,
          "hand_shape": "2443",
          "reason": "Bid \u2663 with only 3 cards"
        },
        {
          "hand_number": 54,
          "position": "West",
          "bid": "4\u2665",
          "hand_hcp": 12,
          "hand_total_points": 14,
          "hand_shape": "5305",
          "reason": "Bid \u2665 with only 3 cards"
        },
        {
          "hand_number": 56,
          "position": "West",
          "bid": "2\u2666",
          "hand_hcp": 6,
          "hand_total_points": 6,
          "hand_shape": "4333",
          "reason": "Bid \u2666 with only 3 cards"
        },
        {
          "hand_number": 73,
          "position": "West",
          "bid": "2\u2666",
          "hand_hcp": 11,
          "hand_total_points": 12,
          "hand_shape": "4531",
          "reason": "Bid \u2666 with only 3 cards"
        }
      ],
      "conventions": [
        {
          "hand_number": 15,
          "position": "South",
          "convention": "Stayman",
          "error": "Used Stayman without 4-card major",
          "hand_hcp": 9,
          "spades": 2,
          "hearts": 3
        },
        {
          "hand_number": 348,
          "position": "West",
          "convention": "Stayman",
          "error": "Used Stayman without 4-card major",
          "hand_hcp": 11,
          "spades": 0,
          "hearts": 3
        },
        {
          "hand_number": 463,
          "position": "West",
          "convention": "Stayman",
          "error": "Used Stayman without 4-card major",
          "hand_hcp": 9,
          "spades": 1,
          "hearts": 3
        }
      ],
      "game_slam": [
        {
          "hand_number": 1,
          "error": "Stopped below game in major with 25+ points",
          "combined_points": 30,
          "final_contract": "2\u2665"
        },
        {
          "hand_number": 7,
          "error": "Stopped below game in major with 25+ points",
          "combined_points": 25,
          "final_contract": "3\u2665"
        },
        {
          "hand_number": 11,
          "error": "Stopped below game in major with 25+ points",
          "combined_points": 25,
          "final_contract": "3\u2660"
        },
        {
          "hand_number": 14,
          "error": "Stopped below game in major with 25+ points",
          "combined_points": 29,
          "final_contract": "1\u2660"
        },
        {
          "hand_number": 31,
          "error": "Stopped below game in major with 25+ points",
          "combined_points": 27,
          "final_contract": "1\u2660"
        },
        {
          "hand_number": 34,
          "error": "Stopped below game in major with 25+ points",
          "combined_points": 35,
          "final_contract": "2\u2660"
        },
        {
          "hand_number": 39,
          "error": "Stopped below game in major with 25+ points",
          "combined_points": 25,
          "final_contract": "1\u2660"
        },
        {
          "hand_number": 40,
          "error": "Stopped below game with 25+ points",
          "combined_points": 27,
          "final_contract": "2NT"
        },
        {
          "hand_number": 42,
          "error": "Stopped below game in major with 25+ points",
          "combined_points": 33,
          "final_contract": "3\u2660"
        },
        {
          "hand_number": 51,
          "error": "Stopped below game with 25+ points",
          "combined_points": 25,
          "final_contract": "2\u2666"
        }
      ]
    },
    "reasonableness_breakdown": {
      "excellent": 300,
      "good": 608,
      "questionable": 0,
      "poor": 49,
      "terrible": 3
    },
    "grade": "B (Good, minor issues)"
  },
  "all_errors": {
    "legality": [],
    "appropriateness": [
      {
        "hand_number": 1,
        "position": "East",
        "bid": "2\u2666",
        "hand_hcp": 12,
        "hand_total_points": 13,
        "hand_shape": "1534",
        "reason": "Bid \u2666 with only 3 cards"
      },
      {
        "hand_number": 1,
        "position": "West",
        "bid": "2\u2665",
        "hand_hcp": 17,
        "hand_total_points": 17,
        "hand_shape": "2344",
        "reason": "Bid \u2665 with only 3 cards"
      },
      {
        "hand_number": 15,
        "position": "North",
        "bid": "4\u2663",
        "hand_hcp": 12,
        "hand_total_points": 12,
        "hand_shape": "3433",
        "reason": "Bid \u2663 with only 3 cards"
      },
      {
        "hand_number": 25,
        "position": "East",
        "bid": "4\u2665",
        "hand_hcp": 14,
        "hand_total_points": 16,
        "hand_shape": "2362",
        "reason": "Bid \u2665 with only 3 cards"
      },
      {
        "hand_number": 33,
        "position": "South",
        "bid": "2\u2663",
        "hand_hcp": 9,
        "hand_total_points": 9,
        "hand_shape": "4243",
        "reason": "Bid \u2663 with only 3 cards"
      },
      {
        "hand_number": 34,
        "position": "South",
        "bid": "2\u2665",
        "hand_hcp": 18,
        "hand_total_points": 20,
        "hand_shape": "6223",
        "reason": "Bid \u2665 with only 2 cards"
      },
      {
        "hand_number": 52,
        "position": "East",
        "bid": "2\u2663",
        "hand_hcp": 12,
        "hand_total_points": 12,
        "hand_shape": "2443",
        "reason": "Bid \u2663 with only 3 cards"
      },
      {
        "hand_number": 54,
        "position": "West",
        "bid": "4\u2665",
        "hand_hcp": 12,
        "hand_total_points": 14,
        "hand_shape": "5305",
        "reason": "Bid \u2665 with only 3 cards"
      },
      {
        "hand_number": 56,
        "position": "West",
        "bid": "2\u2666",
        "hand_hcp": 6,
        "hand_total_points": 6,
        "hand_shape": "4333",
        "reason": "Bid \u2666 with only 3 cards"
      },
      {
        "hand_number": 73,
        "position": "West",
        "bid": "2\u2666",
        "hand_hcp": 11,
        "hand_total_points": 12,
        "hand_shape": "4531",
        "reason": "Bid \u2666 with only 3 cards"
      },
      {
        "hand_number": 73,
        "position": "East",
        "bid": "2\u2665",
        "hand_hcp": 16,
        "hand_total_points": 16,
        "hand_shape": "4342",
        "reason": "Bid \u2665 with only 3 cards"
      },
      {
        "hand_number": 82,
        "position": "East",
        "bid": "2\u2665",
        "hand_hcp": 15,
        "hand_total_points": 15,
        "hand_shape": "3343",
        "reason": "Bid \u2665 with only 3 cards"
      },
      {
        "hand_number": 88,
        "position": "North",
        "bid": "2\u2665",
        "hand_hcp": 11,
        "hand_total_points": 13,
        "hand_shape": "6241",
        "reason": "Bid \u2665 with only 2 cards"
      },
      {
        "hand_number": 88,
        "position": "South",
        "bid": "2\u2660",
        "hand_hcp": 16,
        "hand_total_points": 17,
        "hand_shape": "3235",
        "reason": "Bid \u2660 with only 3 cards"
      },
      {
        "hand_number": 112,
        "position": "West",
        "bid": "2\u2666",
        "hand_hcp": 9,
        "hand_total_points": 9,
        "hand_shape": "2434",
        "reason": "Bid \u2666 with only 3 cards"
      },
      {
        "hand_number": 116,
        "position": "South",
        "bid": "3\u2665",
        "hand_hcp": 10,
        "hand_total_points": 11,
        "hand_shape": "2335",
        "reason": "Bid \u2665 with only 3 cards"
      },
      {
        "hand_number": 119,
        "position": "East",
        "bid": "3\u2660",
        "hand_hcp": 12,
        "hand_total_points": 12,
        "hand_shape": "3334",
        "reason": "Bid \u2660 with only 3 cards"
      },
      {
        "hand_number": 120,
        "position": "East",
        "bid": "4\u2665",
        "hand_hcp": 18,
        "hand_total_points": 19,
        "hand_shape": "2335",
        "reason": "Bid \u2665 with only 3 cards"
      },
      {
        "hand_number": 123,
        "position": "South",
        "bid": "3\u2665",
        "hand_hcp": 12,
        "hand_total_points": 13,
        "hand_shape": "2335",
        "reason": "Bid \u2665 with only 3 cards"
      },
      {
        "hand_number": 138,
        "position": "South",
        "bid": "2\u2660",
        "hand_hcp": 10,
        "hand_total_points": 10,
        "hand_shape": "3433",
        "reason": "Bid \u2660 with only 3 cards"
      },
      {
        "hand_number": 148,
        "position": "North",
        "bid": "3\u2666",
        "hand_hcp": 11,
        "hand_total_points": 11,
        "hand_shape": "4234",
        "reason": "Bid \u2666 with only 3 cards"
      },
      {
        "hand_number": 154,
        "position": "South",
        "bid": "3\u2665",
        "hand_hcp": 12,
        "hand_total_points": 12,
        "hand_shape": "4333",
        "reason": "Bid \u2665 with only 3 cards"
      },
      {
        "hand_number": 161,
        "position": "South",
        "bid": "4\u2665",
        "hand_hcp": 18,
        "hand_total_points": 18,
        "hand_shape": "2344",
        "reason": "Bid \u2665 with only 3 cards"
      },
      {
        "hand_number": 164,
        "position": "East",
        "bid": "2\u2663",
        "hand_hcp": 22,
        "hand_total_points": 22,
        "hand_shape": "2443",
        "reason": "Bid \u2663 with only 3 cards"
      },
      {
        "hand_number": 165,
        "position": "South",
        "bid": "2\u2665",
        "hand_hcp": 8,
        "hand_total_points": 8,
        "hand_shape": "3334",
        "reason": "Bid \u2665 with only 3 cards"
      },
      {
        "hand_number": 169,
        "position": "North",
        "bid": "3\u2665",
        "hand_hcp": 10,
        "hand_total_points": 11,
        "hand_shape": "2335",
        "reason": "Bid \u2665 with only 3 cards"
      },
      {
        "hand_number": 170,
        "position": "West",
        "bid": "2\u2665",
        "hand_hcp": 7,
        "hand_total_points": 9,
        "hand_shape": "5215",
        "reason": "Bid \u2665 with only 2 cards"
      },
      {
        "hand_number": 170,
        "position": "East",
        "bid": "2\u2660",
        "hand_hcp": 15,
        "hand_total_points": 16,
        "hand_shape": "2533",
        "reason": "Bid \u2660 with only 2 cards"
      },
      {
        "hand_number": 180,
        "position": "South",
        "bid": "3\u2663",
        "hand_hcp": 12,
        "hand_total_points": 12,
        "hand_shape": "4333",
        "reason": "Bid \u2663 with only 3 cards"
      },
      {
        "hand_number": 187,
        "position": "North",
        "bid": "3\u2666",
        "hand_hcp": 10,
        "hand_total_points": 10,
        "hand_shape": "3334",
        "reason": "Bid \u2666 with only 3 cards"
      },
      {
        "hand_number": 196,
        "position": "West",
        "bid": "2\u2663",
        "hand_hcp": 9,
        "hand_total_points": 9,
        "hand_shape": "4243",
        "reason": "Bid \u2663 with only 3 cards"
      },
      {
        "hand_number": 207,
        "position": "North",
        "bid": "2\u2663",
        "hand_hcp": 9,
        "hand_total_points": 10,
        "hand_shape": "5233",
        "reason": "Bid \u2663 with only 3 cards"
      },
      {
        "hand_number": 216,
        "position": "East",
        "bid": "4\u2665",
        "hand_hcp": 15,
        "hand_total_points": 16,
        "hand_shape": "2335",
        "reason": "Bid \u2665 with only 3 cards"
      },
      {
        "hand_number": 217,
        "position": "South",
        "bid": "3\u2665",
        "hand_hcp": 12,
        "hand_total_points": 13,
        "hand_shape": "2335",
        "reason": "Bid \u2665 with only 3 cards"
      },
      {
        "hand_number": 221,
        "position": "South",
        "bid": "2\u2660",
        "hand_hcp": 16,
        "hand_total_points": 17,
        "hand_shape": "3352",
        "reason": "Bid \u2660 with only 3 cards"
      },
      {
        "hand_number": 226,
        "position": "West",
        "bid": "2\u2663",
        "hand_hcp": 8,
        "hand_total_points": 8,
        "hand_shape": "3343",
        "reason": "Bid \u2663 with only 3 cards"
      },
      {
        "hand_number": 229,
        "position": "West",
        "bid": "2\u2660",
        "hand_hcp": 7,
        "hand_total_points": 7,
        "hand_shape": "3343",
        "reason": "Bid \u2660 with only 3 cards"
      },
      {
        "hand_number": 232,
        "position": "South",
        "bid": "4\u2663",
        "hand_hcp": 12,
        "hand_total_points": 13,
        "hand_shape": "2533",
        "reason": "Bid \u2663 with only 3 cards"
      },
      {
        "hand_number": 240,
        "position": "West",
        "bid": "2\u2666",
        "hand_hcp": 6,
        "hand_total_points": 7,
        "hand_shape": "5332",
        "reason": "Bid \u2666 with only 3 cards"
      },
      {
        "hand_number": 241,
        "position": "South",
        "bid": "2\u2663",
        "hand_hcp": 7,
        "hand_total_points": 7,
        "hand_shape": "4243",
        "reason": "Bid \u2663 with only 3 cards"
      },
      {
        "hand_number": 245,
        "position": "West",
        "bid": "3\u2665",
        "hand_hcp": 10,
        "hand_total_points": 11,
        "hand_shape": "2353",
        "reason": "Bid \u2665 with only 3 cards"
      },
      {
        "hand_number": 257,
        "position": "South",
        "bid": "3\u2665",
        "hand_hcp": 10,
        "hand_total_points": 11,
        "hand_shape": "4315",
        "reason": "Bid \u2665 with only 3 cards"
      },
      {
        "hand_number": 258,
        "position": "West",
        "bid": "2\u2663",
        "hand_hcp": 6,
        "hand_total_points": 6,
        "hand_shape": "3343",
        "reason": "Bid \u2663 with only 3 cards"
      },
      {
        "hand_number": 262,
        "position": "West",
        "bid": "2\u2663",
        "hand_hcp": 13,
        "hand_total_points": 15,
        "hand_shape": "0463",
        "reason": "Bid \u2663 with only 3 cards"
      },
      {
        "hand_number": 266,
        "position": "South",
        "bid": "4\u2665",
        "hand_hcp": 12,
        "hand_total_points": 12,
        "hand_shape": "4333",
        "reason": "Bid \u2665 with only 3 cards"
      },
      {
        "hand_number": 274,
        "position": "West",
        "bid": "2\u2660",
        "hand_hcp": 9,
        "hand_total_points": 9,
        "hand_shape": "3334",
        "reason": "Bid \u2660 with only 3 cards"
      },
      {
        "hand_number": 280,
        "position": "South",
        "bid": "2\u2666",
        "hand_hcp": 8,
        "hand_total_points": 9,
        "hand_shape": "2533",
        "reason": "Bid \u2666 with only 3 cards"
      },
      {
        "hand_number": 281,
        "position": "South",
        "bid": "2\u2665",
        "hand_hcp": 11,
        "hand_total_points": 15,
        "hand_shape": "5107",
        "reason": "Bid \u2665 with only 1 cards"
      },
      {
        "hand_number": 281,
        "position": "North",
        "bid": "2\u2660",
        "hand_hcp": 15,
        "hand_total_points": 15,
        "hand_shape": "2344",
        "reason": "Bid \u2660 with only 2 cards"
      },
      {
        "hand_number": 282,
        "position": "West",
        "bid": "3\u2666",
        "hand_hcp": 11,
        "hand_total_points": 12,
        "hand_shape": "3235",
        "reason": "Bid \u2666 with only 3 cards"
      },
      {
        "hand_number": 289,
        "position": "West",
        "bid": "2\u2666",
        "hand_hcp": 7,
        "hand_total_points": 8,
        "hand_shape": "5134",
        "reason": "Bid \u2666 with only 3 cards"
      },
      {
        "hand_number": 312,
        "position": "East",
        "bid": "3\u2660",
        "hand_hcp": 11,
        "hand_total_points": 11,
        "hand_shape": "3433",
        "reason": "Bid \u2660 with only 3 cards"
      },
      {
        "hand_number": 333,
        "position": "West",
        "bid": "2\u2666",
        "hand_hcp": 10,
        "hand_total_points": 13,
        "hand_shape": "0625",
        "reason": "Bid \u2666 with only 2 cards"
      },
      {
        "hand_number": 333,
        "position": "East",
        "bid": "2\u2665",
        "hand_hcp": 16,
        "hand_total_points": 16,
        "hand_shape": "2344",
        "reason": "Bid \u2665 with only 3 cards"
      },
      {
        "hand_number": 337,
        "position": "North",
        "bid": "2\u2665",
        "hand_hcp": 8,
        "hand_total_points": 8,
        "hand_shape": "3334",
        "reason": "Bid \u2665 with only 3 cards"
      },
      {
        "hand_number": 345,
        "position": "East",
        "bid": "2\u2663",
        "hand_hcp": 8,
        "hand_total_points": 8,
        "hand_shape": "4432",
        "reason": "Bid \u2663 with only 2 cards"
      },
      {
        "hand_number": 352,
        "position": "North",
        "bid": "2\u2660",
        "hand_hcp": 6,
        "hand_total_points": 7,
        "hand_shape": "3235",
        "reason": "Bid \u2660 with only 3 cards"
      },
      {
        "hand_number": 357,
        "position": "East",
        "bid": "2\u2660",
        "hand_hcp": 15,
        "hand_total_points": 16,
        "hand_shape": "3352",
        "reason": "Bid \u2660 with only 3 cards"
      },
      {
        "hand_number": 361,
        "position": "South",
        "bid": "2\u2666",
        "hand_hcp": 7,
        "hand_total_points": 7,
        "hand_shape": "4234",
        "reason": "Bid \u2666 with only 3 cards"
      },
      {
        "hand_number": 370,
        "position": "West",
        "bid": "2\u2666",
        "hand_hcp": 9,
        "hand_total_points": 9,
        "hand_shape": "2434",
        "reason": "Bid \u2666 with only 3 cards"
      },
      {
        "hand_number": 375,
        "position": "West",
        "bid": "2\u2665",
        "hand_hcp": 7,
        "hand_total_points": 9,
        "hand_shape": "6331",
        "reason": "Bid \u2665 with only 3 cards"
      },
      {
        "hand_number": 379,
        "position": "East",
        "bid": "2\u2663",
        "hand_hcp": 8,
        "hand_total_points": 8,
        "hand_shape": "4333",
        "reason": "Bid \u2663 with only 3 cards"
      },
      {
        "hand_number": 384,
        "position": "West",
        "bid": "3\u2666",
        "hand_hcp": 12,
        "hand_total_points": 12,
        "hand_shape": "3433",
        "reason": "Bid \u2666 with only 3 cards"
      },
      {
        "hand_number": 390,
        "position": "East",
        "bid": "2\u2666",
        "hand_hcp": 6,
        "hand_total_points": 7,
        "hand_shape": "2533",
        "reason": "Bid \u2666 with only 3 cards"
      },
      {
        "hand_number": 393,
        "position": "North",
        "bid": "2\u2660",
        "hand_hcp": 7,
        "hand_total_points": 8,
        "hand_shape": "3235",
        "reason": "Bid \u2660 with only 3 cards"
      },
      {
        "hand_number": 397,
        "position": "East",
        "bid": "2\u2665",
        "hand_hcp": 11,
        "hand_total_points": 12,
        "hand_shape": "5233",
        "reason": "Bid \u2665 with only 2 cards"
      },
      {
        "hand_number": 397,
        "position": "West",
        "bid": "2\u2660",
        "hand_hcp": 17,
        "hand_total_points": 17,
        "hand_shape": "3334",
        "reason": "Bid \u2660 with only 3 cards"
      },
      {
        "hand_number": 410,
        "position": "West",
        "bid": "4\u2660",
        "hand_hcp": 16,
        "hand_total_points": 17,
        "hand_shape": "3235",
        "reason": "Bid \u2660 with only 3 cards"
      },
      {
        "hand_number": 418,
        "position": "West",
        "bid": "3\u2665",
        "hand_hcp": 12,
        "hand_total_points": 13,
        "hand_shape": "2353",
        "reason": "Bid \u2665 with only 3 cards"
      },
      {
        "hand_number": 419,
        "position": "West",
        "bid": "3\u2663",
        "hand_hcp": 12,
        "hand_total_points": 12,
        "hand_shape": "3433",
        "reason": "Bid \u2663 with only 3 cards"
      },
      {
        "hand_number": 429,
        "position": "West",
        "bid": "3\u2666",
        "hand_hcp": 10,
        "hand_total_points": 11,
        "hand_shape": "2335",
        "reason": "Bid \u2666 with only 3 cards"
      },
      {
        "hand_number": 431,
        "position": "West",
        "bid": "2\u2660",
        "hand_hcp": 9,
        "hand_total_points": 10,
        "hand_shape": "3532",
        "reason": "Bid \u2660 with only 3 cards"
      },
      {
        "hand_number": 436,
        "position": "East",
        "bid": "2\u2663",
        "hand_hcp": 11,
        "hand_total_points": 13,
        "hand_shape": "2461",
        "reason": "Bid \u2663 with only 1 cards"
      },
      {
        "hand_number": 436,
        "position": "West",
        "bid": "2\u2666",
        "hand_hcp": 16,
        "hand_total_points": 17,
        "hand_shape": "3325",
        "reason": "Bid \u2666 with only 2 cards"
      },
      {
        "hand_number": 442,
        "position": "West",
        "bid": "2\u2666",
        "hand_hcp": 8,
        "hand_total_points": 9,
        "hand_shape": "1534",
        "reason": "Bid \u2666 with only 3 cards"
      },
      {
        "hand_number": 442,
        "position": "East",
        "bid": "2\u2665",
        "hand_hcp": 16,
        "hand_total_points": 16,
        "hand_shape": "2344",
        "reason": "Bid \u2665 with only 3 cards"
      },
      {
        "hand_number": 460,
        "position": "West",
        "bid": "3\u2660",
        "hand_hcp": 12,
        "hand_total_points": 12,
        "hand_shape": "3244",
        "reason": "Bid \u2660 with only 3 cards"
      },
      {
        "hand_number": 465,
        "position": "North",
        "bid": "2\u2665",
        "hand_hcp": 6,
        "hand_total_points": 8,
        "hand_shape": "2326",
        "reason": "Bid \u2665 with only 3 cards"
      },
      {
        "hand_number": 469,
        "position": "South",
        "bid": "4\u2660",
        "hand_hcp": 15,
        "hand_total_points": 15,
        "hand_shape": "3343",
        "reason": "Bid \u2660 with only 3 cards"
      },
      {
        "hand_number": 473,
        "position": "West",
        "bid": "3\u2663",
        "hand_hcp": 10,
        "hand_total_points": 10,
        "hand_shape": "4333",
        "reason": "Bid \u2663 with only 3 cards"
      },
      {
        "hand_number": 477,
        "position": "South",
        "bid": "4\u2665",
        "hand_hcp": 17,
        "hand_total_points": 17,
        "hand_shape": "4333",
        "reason": "Bid \u2665 with only 3 cards"
      },
      {
        "hand_number": 481,
        "position": "North",
        "bid": "3\u2665",
        "hand_hcp": 10,
        "hand_total_points": 10,
        "hand_shape": "3334",
        "reason": "Bid \u2665 with only 3 cards"
      },
      {
        "hand_number": 486,
        "position": "North",
        "bid": "2\u2666",
        "hand_hcp": 6,
        "hand_total_points": 7,
        "hand_shape": "1435",
        "reason": "Bid \u2666 with only 3 cards"
      },
      {
        "hand_number": 495,
        "position": "South",
        "bid": "2\u2665",
        "hand_hcp": 9,
        "hand_total_points": 9,
        "hand_shape": "2344",
        "reason": "Bid \u2665 with only 3 cards"
      }
    ],
    "conventions": [
      {
        "hand_number": 15,
        "position": "South",
        "convention": "Stayman",
        "error": "Used Stayman without 4-card major",
        "hand_hcp": 9,
        "spades": 2,
        "hearts": 3
      },
      {
        "hand_number": 348,
        "position": "West",
        "convention": "Stayman",
        "error": "Used Stayman without 4-card major",
        "hand_hcp": 11,
        "spades": 0,
        "hearts": 3
      },
      {
        "hand_number": 463,
        "position": "West",
        "convention": "Stayman",
        "error": "Used Stayman without 4-card major",
        "hand_hcp": 9,
        "spades": 1,
        "hearts": 3
      }
    ],
    "game_slam": [
      {
        "hand_number": 1,
        "error": "Stopped below game in major with 25+ points",
        "combined_points": 30,
        "final_contract": "2\u2665"
      },
      {
        "hand_number": 7,
        "error": "Stopped below game in major with 25+ points",
        "combined_points": 25,
        "final_contract": "3\u2665"
      },
      {
        "hand_number": 11,
        "error": "Stopped below game in major with 25+ points",
        "combined_points": 25,
        "final_contract": "3\u2660"
      },
      {
        "hand_number": 14,
        "error": "Stopped below game in major with 25+ points",
        "combined_points": 29,
        "final_contract": "1\u2660"
      },
      {
        "hand_number": 31,
        "error": "Stopped below game in major with 25+ points",
        "combined_points": 27,
        "final_contract": "1\u2660"
      },
      {
        "hand_number": 34,
        "error": "Stopped below game in major with 25+ points",
        "combined_points": 35,
        "final_contract": "2\u2660"
      },
      {
        "hand_number": 39,
        "error": "Stopped below game in major with 25+ points",
        "combined_points": 25,
        "final_contract": "1\u2660"
      },
      {
        "hand_number": 40,
        "error": "Stopped below game with 25+ points",
        "combined_points": 27,
        "final_contract": "2NT"
      },
      {
        "hand_number": 42,
        "error": "Stopped below game in major with 25+ points",
        "combined_points": 33,
        "final_contract": "3\u2660"
      },
      {
        "hand_number": 51,
        "error": "Stopped below game with 25+ points",
        "combined_points": 25,
        "final_contract": "2\u2666"
      },
      {
        "hand_number": 57,
        "error": "Stopped below game in major with 25+ points",
        "combined_points": 25,
        "final_contract": "1\u2665"
      },
      {
        "hand_number": 58,
        "error": "Stopped below game in major with 25+ points",
        "combined_points": 35,
        "final_contract": "1\u2660"
      },
      {
        "hand_number": 64,
        "error": "Stopped below game in major with 25+ points",
        "combined_points": 25,
        "final_contract": "1\u2660"
      },
      {
        "hand_number": 66,
        "error": "Stopped below game in major with 25+ points",
        "combined_points": 31,
        "final_contract": "1\u2660"
      },
      {
        "hand_number": 70,
        "error": "Stopped below game with 25+ points",
        "combined_points": 29,
        "final_contract": "2\u2666"
      },
      {
        "hand_number": 72,
        "error": "Stopped below game with 25+ points",
        "combined_points": 28,
        "final_contract": "2\u2666"
      },
      {
        "hand_number": 73,
        "error": "Stopped below game in major with 25+ points",
        "combined_points": 28,
        "final_contract": "2\u2665"
      },
      {
        "hand_number": 78,
        "error": "Stopped below game with 25+ points",
        "combined_points": 25,
        "final_contract": "1NT"
      },
      {
        "hand_number": 80,
        "error": "Stopped below game with 25+ points",
        "combined_points": 29,
        "final_contract": "1\u2663"
      },
      {
        "hand_number": 82,
        "error": "Stopped below game in major with 25+ points",
        "combined_points": 36,
        "final_contract": "2\u2665"
      },
      {
        "hand_number": 87,
        "error": "Stopped below game with 25+ points",
        "combined_points": 26,
        "final_contract": "2\u2666"
      },
      {
        "hand_number": 88,
        "error": "Stopped below game in major with 25+ points",
        "combined_points": 30,
        "final_contract": "2\u2660"
      },
      {
        "hand_number": 103,
        "error": "Stopped below game with 25+ points",
        "combined_points": 27,
        "final_contract": "1\u2666"
      },
      {
        "hand_number": 106,
        "error": "Stopped below game with 25+ points",
        "combined_points": 30,
        "final_contract": "2\u2666"
      },
      {
        "hand_number": 114,
        "error": "Stopped below game in major with 25+ points",
        "combined_points": 36,
        "final_contract": "2\u2660"
      },
      {
        "hand_number": 116,
        "error": "Stopped below game in major with 25+ points",
        "combined_points": 25,
        "final_contract": "3\u2665"
      },
      {
        "hand_number": 118,
        "error": "Stopped below game in major with 25+ points",
        "combined_points": 33,
        "final_contract": "2\u2665"
      },
      {
        "hand_number": 119,
        "error": "Stopped below game in major with 25+ points",
        "combined_points": 25,
        "final_contract": "3\u2660"
      },
      {
        "hand_number": 123,
        "error": "Stopped below game in major with 25+ points",
        "combined_points": 26,
        "final_contract": "3\u2665"
      },
      {
        "hand_number": 136,
        "error": "Stopped below game with 25+ points",
        "combined_points": 25,
        "final_contract": "2\u2663"
      },
      {
        "hand_number": 139,
        "error": "Stopped below game with 25+ points",
        "combined_points": 25,
        "final_contract": "2NT"
      },
      {
        "hand_number": 155,
        "error": "Stopped below game in major with 25+ points",
        "combined_points": 27,
        "final_contract": "3\u2665"
      },
      {
        "hand_number": 162,
        "error": "Stopped below game in major with 25+ points",
        "combined_points": 26,
        "final_contract": "3\u2660"
      },
      {
        "hand_number": 166,
        "error": "Stopped below game in major with 25+ points",
        "combined_points": 28,
        "final_contract": "1\u2665"
      },
      {
        "hand_number": 175,
        "error": "Stopped below game with 25+ points",
        "combined_points": 26,
        "final_contract": "2\u2666"
      },
      {
        "hand_number": 189,
        "error": "Stopped below game with 25+ points",
        "combined_points": 25,
        "final_contract": "1NT"
      },
      {
        "hand_number": 197,
        "error": "Stopped below game with 25+ points",
        "combined_points": 31,
        "final_contract": "2NT"
      },
      {
        "hand_number": 203,
        "error": "Stopped below game with 25+ points",
        "combined_points": 25,
        "final_contract": "1NT"
      },
      {
        "hand_number": 209,
        "error": "Stopped below game in major with 25+ points",
        "combined_points": 27,
        "final_contract": "3\u2665"
      },
      {
        "hand_number": 210,
        "error": "Stopped below game in major with 25+ points",
        "combined_points": 25,
        "final_contract": "3\u2660"
      },
      {
        "hand_number": 213,
        "error": "Stopped below game in major with 25+ points",
        "combined_points": 32,
        "final_contract": "2\u2665"
      },
      {
        "hand_number": 221,
        "error": "Stopped below game in major with 25+ points",
        "combined_points": 30,
        "final_contract": "2\u2660"
      },
      {
        "hand_number": 223,
        "error": "Stopped below game in major with 25+ points",
        "combined_points": 25,
        "final_contract": "2\u2665"
      },
      {
        "hand_number": 224,
        "error": "Stopped below game with 25+ points",
        "combined_points": 31,
        "final_contract": "1\u2663"
      },
      {
        "hand_number": 227,
        "error": "Stopped below game with 25+ points",
        "combined_points": 25,
        "final_contract": "2\u2666"
      },
      {
        "hand_number": 230,
        "error": "Stopped below game in major with 25+ points",
        "combined_points": 25,
        "final_contract": "3\u2660"
      },
      {
        "hand_number": 235,
        "error": "Stopped below game in major with 25+ points",
        "combined_points": 26,
        "final_contract": "2\u2665"
      },
      {
        "hand_number": 238,
        "error": "Stopped below game in major with 25+ points",
        "combined_points": 34,
        "final_contract": "3\u2660"
      },
      {
        "hand_number": 243,
        "error": "Stopped below game in major with 25+ points",
        "combined_points": 27,
        "final_contract": "1\u2665"
      },
      {
        "hand_number": 252,
        "error": "Stopped below game in major with 25+ points",
        "combined_points": 27,
        "final_contract": "1\u2660"
      },
      {
        "hand_number": 258,
        "error": "Stopped below game in major with 25+ points",
        "combined_points": 26,
        "final_contract": "2\u2660"
      },
      {
        "hand_number": 259,
        "error": "Stopped below game with 25+ points",
        "combined_points": 28,
        "final_contract": "1\u2663"
      },
      {
        "hand_number": 262,
        "error": "Stopped below game in major with 25+ points",
        "combined_points": 31,
        "final_contract": "2\u2660"
      },
      {
        "hand_number": 267,
        "error": "Stopped below game in major with 25+ points",
        "combined_points": 27,
        "final_contract": "3\u2660"
      },
      {
        "hand_number": 270,
        "error": "Stopped below game with 25+ points",
        "combined_points": 27,
        "final_contract": "2\u2663"
      },
      {
        "hand_number": 274,
        "error": "Stopped below game in major with 25+ points",
        "combined_points": 27,
        "final_contract": "3\u2660"
      },
      {
        "hand_number": 281,
        "error": "Stopped below game in major with 25+ points",
        "combined_points": 30,
        "final_contract": "2\u2660"
      },
      {
        "hand_number": 284,
        "error": "Stopped below game in major with 25+ points",
        "combined_points": 27,
        "final_contract": "1\u2660"
      },
      {
        "hand_number": 286,
        "error": "Stopped below game with 25+ points",
        "combined_points": 27,
        "final_contract": "1\u2666"
      },
      {
        "hand_number": 288,
        "error": "Stopped below game with 25+ points",
        "combined_points": 31,
        "final_contract": "2NT"
      },
      {
        "hand_number": 297,
        "error": "Stopped below game with 25+ points",
        "combined_points": 28,
        "final_contract": "2\u2663"
      },
      {
        "hand_number": 302,
        "error": "Stopped below game in major with 25+ points",
        "combined_points": 26,
        "final_contract": "3\u2660"
      },
      {
        "hand_number": 324,
        "error": "Stopped below game in major with 25+ points",
        "combined_points": 31,
        "final_contract": "1\u2665"
      },
      {
        "hand_number": 325,
        "error": "Stopped below game with 25+ points",
        "combined_points": 28,
        "final_contract": "1\u2666"
      },
      {
        "hand_number": 332,
        "error": "Stopped below game with 25+ points",
        "combined_points": 27,
        "final_contract": "1\u2663"
      },
      {
        "hand_number": 333,
        "error": "Stopped below game in major with 25+ points",
        "combined_points": 29,
        "final_contract": "2\u2665"
      },
      {
        "hand_number": 341,
        "error": "Stopped below game in major with 25+ points",
        "combined_points": 34,
        "final_contract": "3\u2660"
      },
      {
        "hand_number": 349,
        "error": "Stopped below game with 25+ points",
        "combined_points": 30,
        "final_contract": "2\u2666"
      },
      {
        "hand_number": 353,
        "error": "Stopped below game with 25+ points",
        "combined_points": 25,
        "final_contract": "2NT"
      },
      {
        "hand_number": 357,
        "error": "Stopped below game in major with 25+ points",
        "combined_points": 26,
        "final_contract": "2\u2660"
      },
      {
        "hand_number": 387,
        "error": "Stopped below game with 25+ points",
        "combined_points": 26,
        "final_contract": "2\u2666"
      },
      {
        "hand_number": 394,
        "error": "Stopped below game in major with 25+ points",
        "combined_points": 29,
        "final_contract": "1\u2660"
      },
      {
        "hand_number": 401,
        "error": "Stopped below game in major with 25+ points",
        "combined_points": 28,
        "final_contract": "2\u2660"
      },
      {
        "hand_number": 402,
        "error": "Stopped below game in major with 25+ points",
        "combined_points": 31,
        "final_contract": "2\u2660"
      },
      {
        "hand_number": 406,
        "error": "Stopped below game with 25+ points",
        "combined_points": 41,
        "final_contract": "2\u2666"
      },
      {
        "hand_number": 409,
        "error": "Stopped below game in major with 25+ points",
        "combined_points": 29,
        "final_contract": "2\u2665"
      },
      {
        "hand_number": 413,
        "error": "Stopped below game with 25+ points",
        "combined_points": 29,
        "final_contract": "1\u2663"
      },
      {
        "hand_number": 422,
        "error": "Stopped below game in major with 25+ points",
        "combined_points": 25,
        "final_contract": "3\u2660"
      },
      {
        "hand_number": 426,
        "error": "Stopped below game in major with 25+ points",
        "combined_points": 26,
        "final_contract": "1\u2660"
      },
      {
        "hand_number": 431,
        "error": "Stopped below game in major with 25+ points",
        "combined_points": 27,
        "final_contract": "3\u2660"
      },
      {
        "hand_number": 433,
        "error": "Stopped below game in major with 25+ points",
        "combined_points": 25,
        "final_contract": "1\u2665"
      },
      {
        "hand_number": 436,
        "error": "Stopped below game with 25+ points",
        "combined_points": 30,
        "final_contract": "2\u2666"
      },
      {
        "hand_number": 438,
        "error": "Stopped below game in major with 25+ points",
        "combined_points": 30,
        "final_contract": "1\u2665"
      },
      {
        "hand_number": 441,
        "error": "Stopped below game with 25+ points",
        "combined_points": 31,
        "final_contract": "2\u2663"
      },
      {
        "hand_number": 446,
        "error": "Stopped below game in major with 25+ points",
        "combined_points": 31,
        "final_contract": "3\u2660"
      },
      {
        "hand_number": 450,
        "error": "Stopped below game with 25+ points",
        "combined_points": 30,
        "final_contract": "1\u2663"
      },
      {
        "hand_number": 456,
        "error": "Stopped below game in major with 25+ points",
        "combined_points": 25,
        "final_contract": "3\u2660"
      },
      {
        "hand_number": 459,
        "error": "Stopped below game in major with 25+ points",
        "combined_points": 25,
        "final_contract": "1\u2660"
      },
      {
        "hand_number": 472,
        "error": "Stopped below game with 25+ points",
        "combined_points": 29,
        "final_contract": "2\u2666"
      },
      {
        "hand_number": 474,
        "error": "Stopped below game in major with 25+ points",
        "combined_points": 25,
        "final_contract": "1\u2660"
      },
      {
        "hand_number": 476,
        "error": "Stopped below game in major with 25+ points",
        "combined_points": 29,
        "final_contract": "1\u2660"
      },
      {
        "hand_number": 480,
        "error": "Stopped below game with 25+ points",
        "combined_points": 27,
        "final_contract": "2\u2666"
      },
      {
        "hand_number": 487,
        "error": "Stopped below game in major with 25+ points",
        "combined_points": 30,
        "final_contract": "2\u2660"
      },
      {
        "hand_number": 491,
        "error": "Stopped below game in major with 25+ points",
        "combined_points": 30,
        "final_contract": "1\u2665"
      }
    ]
  }
}